dcmake
